ghidrattd/__init__.py
ghidrattd-0.0.0.dist-info/METADATA
ghidrattd-0.0.0.dist-info/WHEEL
ghidrattd-0.0.0.dist-info/top_level.txt
ghidrattd-0.0.0.dist-info/RECORD
