Metadata-Version: 2.1
Name: ghidrattd
Version: 0.0.0
Summary: Coming soon
Author-email: David Millar <vx000@me.com>
